odoo_repl/__init__.py
odoo_repl/access.py
odoo_repl/addons.py
odoo_repl/buildout.py
odoo_repl/color.py
odoo_repl/config.py
odoo_repl/fields.py
odoo_repl/forensics.py
odoo_repl/fzf.py
odoo_repl/gitsources.py
odoo_repl/grep.py
odoo_repl/imports.py
odoo_repl/methods.py
odoo_repl/models.py
odoo_repl/opdb.py
odoo_repl/py.typed
odoo_repl/records.py
odoo_repl/run.py
odoo_repl/search.py
odoo_repl/shell.py
odoo_repl/shorthand.py
odoo_repl/sources.py
odoo_repl/tests.py
odoo_repl/util.py
odoo_repl-0.0.3.dist-info/LICENSE
odoo_repl-0.0.3.dist-info/METADATA
odoo_repl-0.0.3.dist-info/WHEEL
odoo_repl-0.0.3.dist-info/entry_points.txt
odoo_repl-0.0.3.dist-info/top_level.txt
odoo_repl-0.0.3.dist-info/RECORD
