Metadata-Version: 2.1
Name: odoo-repl
Version: 0.0.3
Summary: Enhanced interactive Odoo shell
Home-page: https://github.com/janverb/odoo-repl
Author: Jan Verbeek
Author-email: jan.verbeek@posteo.nl
License: LGPLv3+
Keywords: Odoo Interactive Shell REPL
Platform: UNKNOWN
Classifier: Framework :: Odoo
Classifier: Framework :: Buildout
Classifier: Development Status :: 3 - Alpha
Classifier: License :: OSI Approved :: GNU Lesser General Public License v3 or later (LGPLv3+)
Classifier: Intended Audience :: Developers
Classifier: Environment :: Console
Classifier: Programming Language :: Python :: 2
Classifier: Programming Language :: Python :: 3
Classifier: Topic :: Software Development
Requires-Dist: Pygments
